LICENSE
README.md
setup.py
bin/dbnn
dbnn/__init__.py
dbnn/dbnn.py
dbnn.egg-info/PKG-INFO
dbnn.egg-info/SOURCES.txt
dbnn.egg-info/dependency_links.txt
dbnn.egg-info/requires.txt
dbnn.egg-info/top_level.txt